README.rst
burned.zip
screenshot.png
setup.py
docs/HISTORY.txt
docs/INSTALL.txt
docs/LICENSE.GPL
docs/LICENSE.txt
plonetheme/__init__.py
plonetheme.burned.egg-info/PKG-INFO
plonetheme.burned.egg-info/SOURCES.txt
plonetheme.burned.egg-info/dependency_links.txt
plonetheme.burned.egg-info/entry_points.txt
plonetheme.burned.egg-info/namespace_packages.txt
plonetheme.burned.egg-info/requires.txt
plonetheme.burned.egg-info/top_level.txt
plonetheme/burned/__init__.py
plonetheme/burned/configure.zcml
plonetheme/burned/profiles/default/metadata.xml
plonetheme/burned/profiles/default/theme.xml
plonetheme/burned/static/default.css
plonetheme/burned/static/index.html
plonetheme/burned/static/license.txt
plonetheme/burned/static/manifest.cfg
plonetheme/burned/static/rules.xml
plonetheme/burned/static/images/a1.jpg
plonetheme/burned/static/images/a2.jpg
plonetheme/burned/static/images/a3.jpg
plonetheme/burned/static/images/a4.jpg